{
    "name": "project unit 3",
    "description": "",
    "dependencies": {
        "device": "*"
    },
    "files": [
        "main.blocks",
        "main.ts",
        "README.md",
        "assets.json",
        "images.g.jres",
        "images.g.ts"
    ],
    "testFiles": [
        "test.ts"
    ],
    "targetVersions": {
        "branch": "v1.12.41",
        "tag": "v1.12.41",
        "commits": "https://github.com/microsoft/pxt-arcade/commits/58673437825ecb93a220c8f58a6f9bb5693896ba",
        "target": "1.12.46",
        "pxt": "8.5.52",
        "targetId": "arcade"
    },
    "supportedTargets": [
        "arcade"
    ],
    "preferredEditor": "blocksprj",
    "palette": [
        "#000000",
        "#FFFFFF",
        "#EC9393",
        "#DDD5E2",
        "#F8E1AF",
        "#BC9FB7",
        "#249CA3",
        "#BB9BB6",
        "#A5B8D9",
        "#C2EAEF",
        "#C4BACA",
        "#A4839F",
        "#5C406c",
        "#E5CDC4",
        "#91463d",
        "#000000"
    ]
}
